task3_pipeline_design.v
// -----------------------------
// 4-Stage Pipelined Processor
// -----------------------------
module pipeline_processor (
    input clk,
    input reset
);

    reg [7:0] instr_mem [0:15];  // Instruction Memory
    reg [7:0] reg_file [0:7];    // Register File

    reg [7:0] IF_ID, ID_EX, EX_MEM, MEM_WB;

    integer i;

    // Initialize
    initial begin
        for (i = 0; i < 8; i = i + 1)
            reg_file[i] = i;

        instr_mem[0] = 8'b00000001; // ADD R0, R1
        instr_mem[1] = 8'b00010010; // SUB R0, R2
        instr_mem[2] = 8'b00100011; // LOAD R0, R3
    end

    always @(posedge clk or posedge reset) begin
        if (reset) begin
            IF_ID <= 0; ID_EX <= 0; EX_MEM <= 0; MEM_WB <= 0;
        end else begin
            // Stage 1: Instruction Fetch
            IF_ID <= instr_mem[IF_ID[3:0]];

            // Stage 2: Instruction Decode
            ID_EX <= IF_ID;

            // Stage 3: Execute
            case (ID_EX[7:6])
                2'b00: EX_MEM <= reg_file[ID_EX[3:2]] + reg_file[ID_EX[1:0]]; // ADD
                2'b01: EX_MEM <= reg_file[ID_EX[3:2]] - reg_file[ID_EX[1:0]]; // SUB
                2'b10: EX_MEM <= reg_file[ID_EX[3:0]]; // LOAD
            endcase

            // Stage 4: Write Back
            MEM_WB <= EX_MEM;
        end
    end

endmodule

task3_pipeline_tb.v
`timescale 1ns/1ps

module tb_pipeline_processor;

    reg clk;
    reg reset;

    pipeline_processor uut (
        .clk(clk),
        .reset(reset)
    );

    always #5 clk = ~clk;  // 10ns clock

    initial begin
        $dumpfile("pipeline.vcd");
        $dumpvars(0, tb_pipeline_processor);

        clk = 0;
        reset = 1;
        #10 reset = 0;

        #100 $finish;
    end

endmodule

pipeline.vcd
$date
	Fri Jun 20 01:35:53 2025
$end
$version
	Icarus Verilog
$end
$timescale
	1ps
$end
$scope module tb_pipeline_processor $end
$var reg 1 ! clk $end
$var reg 1 " reset $end
$scope module uut $end
$var wire 1 ! clk $end
$var wire 1 " reset $end
$var reg 8 # EX_MEM [7:0] $end
$var reg 8 $ ID_EX [7:0] $end
$var reg 8 % IF_ID [7:0] $end
$var reg 8 & MEM_WB [7:0] $end
$var integer 32 ' i [31:0] $end
$upscope $end
$upscope $end
$enddefinitions $end
$comment Show the parameter values. $end
$dumpall
$end
#0
$dumpvars
b1000 '
b0 &
b0 %
b0 $
b0 #
1"
0!
$end
#5000
1!
#10000
0!
0"
#15000
b1 %
1!
#20000
0!
#25000
b1 $
b10010 %
1!
#30000
0!
#35000
b1 #
b10010 $
b100011 %
1!
#40000
0!
#45000
b1 &
b10 #
b100011 $
bx %
1!
#50000
0!
#55000
b10 &
b11 #
bx $
1!
#60000
0!
#65000
b11 &
1!
